tests/__init__.py
tests/all_test.py
xtoy/__init__.py
xtoy/classifiers.py
xtoy/evolutionary_search.py
xtoy/featurizers.py
xtoy/first.py
xtoy/multi_output.py
xtoy/prep.py
xtoy/scorers.py
xtoy/scorers_flymake.py
xtoy/toys.py
xtoy/toys_flymake.py
xtoy/treetest.py
xtoy/utils.py
xtoy-0.5.63.dist-info/METADATA
xtoy-0.5.63.dist-info/RECORD
xtoy-0.5.63.dist-info/WHEEL
xtoy-0.5.63.dist-info/top_level.txt
