Metadata-Version: 2.1
Name: xtoy
Version: 0.5.63
Summary: get xtoyed predictions from raw data
Home-page: https://github.com/kootenpv/xtoy
Author: Pascal van Kooten
Author-email: kootenpv@gmail.com
License: MIT
Keywords: data science,machine learning,genetic programming
Platform: any
Classifier: Environment :: Console
Classifier: Intended Audience :: Developers
Classifier: Intended Audience :: Science/Research
Classifier: License :: OSI Approved :: GNU General Public License v3 (GPLv3)
Classifier: Operating System :: Microsoft
Classifier: Operating System :: MacOS :: MacOS X
Classifier: Operating System :: Unix
Classifier: Operating System :: POSIX
Classifier: Programming Language :: Python
Classifier: Programming Language :: Python :: 2.7
Classifier: Programming Language :: Python :: 3
Classifier: Programming Language :: Python :: 3.3
Classifier: Programming Language :: Python :: 3.4
Classifier: Programming Language :: Python :: 3.5
Classifier: Topic :: Scientific/Engineering :: Artificial Intelligence
Classifier: Topic :: Software Development
Classifier: Topic :: Utilities
Requires-Dist: numpy
Requires-Dist: scipy
Requires-Dist: pandas
Requires-Dist: scikit-learn (<0.20,>=0.18.1)
Requires-Dist: xgboost (==0.72.1)
Requires-Dist: lightgbm (==2.2.2)
Requires-Dist: deap
Requires-Dist: bitstring
